pykakasi/__init__.py
pykakasi/__init__.pyi
pykakasi/kakasi.py
pykakasi/kakasi.pyi
pykakasi/kanji.py
pykakasi/kanji.pyi
pykakasi/legacy.py
pykakasi/legacy.pyi
pykakasi/properties.py
pykakasi/properties.pyi
pykakasi/py.typed
pykakasi/scripts.py
pykakasi/scripts.pyi
pykakasi/data/halfkana3.db
pykakasi/data/hepburndict3.db
pykakasi/data/hepburnhira3.db
pykakasi/data/itaijidict4.db
pykakasi/data/kanwadict4.db
pykakasi/data/kunreidict3.db
pykakasi/data/kunreihira3.db
pykakasi/data/passportdict3.db
pykakasi/data/passporthira3.db
pykakasi-2.2.1.data/scripts/kakasi
pykakasi-2.2.1.dist-info/AUTHORS
pykakasi-2.2.1.dist-info/COPYING
pykakasi-2.2.1.dist-info/METADATA
pykakasi-2.2.1.dist-info/WHEEL
pykakasi-2.2.1.dist-info/top_level.txt
pykakasi-2.2.1.dist-info/RECORD
